spu_formal/spu13_formal.sv
// SPU-13 Formal Contract (v1.1)
// Objective: Prove reachability and boundary sanity of the 60-degree manifold.
// Vibe: Correct by Construction.

`default_nettype none

module spu13_formal (
    input  wire        clk,
    input  wire        reset,
    
    // Core Signals to Monitor
    input  wire [2:0]  opcode,
    input  wire [127:0] reg_curr,
    input  wire [127:0] reg_next,
    input  wire        fault_detected,
    input  wire        instr_complete
);

    // --- 1. Internal State for Covers ---
    reg [1:0] seq_state = 0;

`ifdef FORMAL
    // --- 2. Boundary Proofs ---
    always @(*) begin
        // Prove that the zero-sum invariant is always maintained unless a fault is flagged
        if (!reset && !fault_detected) begin
            assert(reg_curr[31:0] + reg_curr[63:32] + reg_curr[95:64] + reg_curr[127:96] == 0);
        end
        
        // Prove that division-by-zero is physically impossible in the Rational LUT
        assert(reg_curr != 128'h0); 
    end

    // --- 3. The "Demo" Traces (Reachability) ---
    always @(posedge clk) begin
        cover(instr_complete && opcode == 3'b000); // ROTR (spin)
        cover(instr_complete && opcode == 3'b001); // TUCK (lock)
        cover(instr_complete && opcode == 3'b110); // ANNE (anneal)
        
        // Complex Sequence: Reset followed by high-tension spin
        if (reset) begin
            seq_state <= 0;
        end else begin
            case (seq_state)
                0: if (opcode == 3'b111) seq_state <= 1; // RESET
                1: if (opcode == 3'b000) seq_state <= 2; // SPIN
                2: cover(1'b1); // Sequence Complete
            endcase
        end
    end
`endif

endmodule

spu_formal/spu13_reachability/engine_0/trace3.vcd
$version Generated by Yosys-SMTBMC $end
$timescale 1ns $end
$var integer 32 t smt_step $end
$var event 1 ! smt_clock $end
$scope module spu13_formal $end
$var wire 1 n0 clk $end
$var wire 1 n1 fault_detected $end
$var wire 1 n2 instr_complete $end
$var wire 3 n3 opcode $end
$var wire 128 n4 reg_curr $end
$var wire 128 n5 reg_next $end
$var wire 1 n6 reset $end
$var wire 2 n7 seq_state $end
$upscope $end
$enddefinitions $end
#0
1!
b00000000000000000000000000000000 t
b1 n0
b0 n1
b1 n2
b111 n3
b00000000000000000000000000000000000000000000000000000000000000000000000000000000000000000000000000000000000000000000000000000000 n4
b00000000000000000000000000000000000000000000000000000000000000000000000000000000000000000000000000000000000000000000000000000000 n5
b0 n6
b00 n7
#5
b0 n0
#10
1!
b00000000000000000000000000000001 t
b1 n0
b0 n1
b0 n2
b000 n3
b00000000000000000000000000000000000000000000000000000000000000000000000000000000000000000000000000000000000000000000000000000000 n4
b00000000000000000000000000000000000000000000000000000000000000000000000000000000000000000000000000000000000000000000000000000000 n5
b0 n6
b01 n7
#15
b0 n0
#20
1!
b00000000000000000000000000000010 t
b1 n0
b0 n1
b0 n2
b111 n3
b00000000000000000000000000000000000000000000000000000000000000000000000000000000000000000000000000000000000000000000000000000000 n4
b00000000000000000000000000000000000000000000000000000000000000000000000000000000000000000000000000000000000000000000000000000000 n5
b0 n6
b10 n7
#25
b0 n0
#30
1!
b00000000000000000000000000000011 t
b1 n0
b0 n1
b0 n2
b111 n3
b00000000000000000000000000000000000000000000000000000000000000000000000000000000000000000000000000000000000000000000000000000000 n4
b00000000000000000000000000000000000000000000000000000000000000000000000000000000000000000000000000000000000000000000000000000000 n5
b0 n6
b10 n7
#35
b0 n0
#40
1!
b00000000000000000000000000000100 t
b1 n0
